MANIFEST.in
README.md
setup.cfg
setup.py
crispy_forms_bulma/__init__.py
crispy_forms_bulma/apps.py
crispy_forms_bulma/bulma.py
crispy_forms_bulma/layout.py
crispy_forms_bulma/settings.py
crispy_forms_bulma.egg-info/PKG-INFO
crispy_forms_bulma.egg-info/SOURCES.txt
crispy_forms_bulma.egg-info/dependency_links.txt
crispy_forms_bulma.egg-info/not-zip-safe
crispy_forms_bulma.egg-info/requires.txt
crispy_forms_bulma.egg-info/top_level.txt
crispy_forms_bulma/templates/bulma/display_form.html
crispy_forms_bulma/templates/bulma/errors.html
crispy_forms_bulma/templates/bulma/field.html
crispy_forms_bulma/templates/bulma/uni_form.html
crispy_forms_bulma/templates/bulma/whole_uni_form.html
crispy_forms_bulma/templates/bulma/layout/baseinput.html
crispy_forms_bulma/templates/bulma/layout/div.html
crispy_forms_bulma/templates/bulma/layout/input_with_icon.html
crispy_forms_bulma/templates/bulma/layout/radioselect.html
crispy_forms_bulma/templatetags/__init__.py
crispy_forms_bulma/templatetags/crispy_forms_bulma_field.py